rmq_interface/__init__.py
rmq_interface/rmq_interface.py
rmq_interface-1.3.0.dist-info/METADATA
rmq_interface-1.3.0.dist-info/WHEEL
rmq_interface-1.3.0.dist-info/top_level.txt
rmq_interface-1.3.0.dist-info/RECORD
